{"dispositions":[{"by_action_event_id":"e_000019","event_id":"e_000017","state":"handled"},{"by_action_event_id":"e_000021","event_id":"e_000018","state":"handled"},{"by_action_event_id":"e_000023","event_id":"e_000020","state":"handled"},{"by_action_event_id":"e_000025","event_id":"e_000022","state":"handled"},{"by_action_event_id":"e_000026","event_id":"e_000024","state":"handled"},{"by_action_event_id":"e_000029","event_id":"e_000027","state":"handled"},{"by_action_event_id":"e_000031","event_id":"e_000028","state":"handled"},{"by_action_event_id":"e_000033","event_id":"e_000030","state":"handled"},{"by_action_event_id":"e_000035","event_id":"e_000032","state":"handled"},{"by_action_event_id":"e_000036","event_id":"e_000034","state":"handled"}],"response_dispositions":[],"timers":[{"anchor_mono_ns":1932000000,"anchor_utc":"2026-01-01T00:00:01.932000+00:00","fire_count":2,"idempotency_key":"sha256:574fae8ae14e26b4b213fccec2962939ce5c5cd77be2986a3c7063c0a67f1f7a","instruction_end_utf16":62,"instruction_event_id":"e_000002","instruction_id":"i_001","instruction_start_utf16":0,"instruction_text":"Remind me every twenty-three minutes to open the amber blinds.","interval_ms":1380000,"message":"open the amber blinds","next_due_mono_ns":4141932000000,"status":"active","timer_id":"t_001"},{"anchor_mono_ns":4211000000,"anchor_utc":"2026-01-01T00:00:04.211000+00:00","fire_count":2,"idempotency_key":"sha256:d175e91d406ca77d33fbe5c5a76708c09a677ee694563cba635820f3aecd3544","instruction_end_utf16":114,"instruction_event_id":"e_000003","instruction_id":"i_002","instruction_start_utf16":29,"instruction_text":"Remind me every twenty-three minutes to open the amber blinds for the notebook draft.","interval_ms":1380000,"message":"open the amber blinds for the notebook draft","next_due_mono_ns":4144211000000,"status":"active","timer_id":"t_002"},{"anchor_mono_ns":6213000000,"anchor_utc":"2026-01-01T00:00:06.213000+00:00","fire_count":2,"idempotency_key":"sha256:582dac8ea8d637aebd4172f7177b2083b6ffdffb7e7799ec4cc70b6e260c5a82","instruction_end_utf16":123,"instruction_event_id":"e_000006","instruction_id":"i_003","instruction_start_utf16":39,"instruction_text":"Remind me every twenty-three minutes to open the amber blinds for the registry page.","interval_ms":1380000,"message":"open the amber blinds for the registry page","next_due_mono_ns":4146213000000,"status":"active","timer_id":"t_003"},{"anchor_mono_ns":8000000000,"anchor_utc":"2026-01-01T00:00:08.000000+00:00","fire_count":2,"idempotency_key":"sha256:ffa93029815552d2ca7f7dcaa6f4f9adce3db139f50fa70c270fa37f3d8864fe","instruction_end_utf16":124,"instruction_event_id":"e_000009","instruction_id":"i_004","instruction_start_utf16":38,"instruction_text":"Remind me every twenty-three minutes to open the amber blinds for the shoreline notes.","interval_ms":1380000,"message":"open the amber blinds for the shoreline notes","next_due_mono_ns":4148000000000,"status":"active","timer_id":"t_004"},{"anchor_mono_ns":10029000000,"anchor_utc":"2026-01-01T00:00:10.029000+00:00","fire_count":2,"idempotency_key":"sha256:432695a4037bd870e03211d15b72bde6f4b46b85578ca8a1a2c57c0cb7aea8b6","instruction_end_utf16":116,"instruction_event_id":"e_000012","instruction_id":"i_005","instruction_start_utf16":31,"instruction_text":"Remind me every twenty-three minutes to open the amber blinds for the cistern sketch.","interval_ms":1380000,"message":"open the amber blinds for the cistern sketch","next_due_mono_ns":4150029000000,"status":"active","timer_id":"t_005"}],"tool_requests":[]}